LICENSE
MANIFEST.in
README.rst
setup.py
ERP.egg-info/PKG-INFO
ERP.egg-info/SOURCES.txt
ERP.egg-info/dependency_links.txt
ERP.egg-info/not-zip-safe
ERP.egg-info/requires.txt
ERP.egg-info/top_level.txt
erp/__init__.py
erp/base/__init__.py
erp/base/article/__init__.py
erp/base/article/admin.py
erp/base/article/api.py
erp/base/article/models.py
erp/base/article/serializers.py
erp/base/article/tests.py
erp/base/article/urls.py
erp/base/article/views.py
erp/base/directory/__init__.py
erp/base/directory/admin.py
erp/base/directory/api.py
erp/base/directory/forms.py
erp/base/directory/models.py
erp/base/directory/serializers.py
erp/base/directory/tests.py
erp/base/directory/urls.py
erp/base/directory/views.py
erp/base/enterprise/__init__.py
erp/base/enterprise/admin.py
erp/base/enterprise/api.py
erp/base/enterprise/forms.py
erp/base/enterprise/models.py
erp/base/enterprise/permissions.py
erp/base/enterprise/serializers.py
erp/base/enterprise/tests.py
erp/base/enterprise/urls.py
erp/base/enterprise/views.py
erp/base/planning/__init__.py
erp/base/planning/admin.py
erp/base/planning/api.py
erp/base/planning/forms.py
erp/base/planning/models.py
erp/base/planning/serializers.py
erp/base/planning/tests.py
erp/base/planning/urls.py
erp/base/planning/validators.py
erp/base/planning/views.py
erp/base/storage/__init__.py
erp/base/storage/admin.py
erp/base/storage/api.py
erp/base/storage/models.py
erp/base/storage/serializers.py
erp/base/storage/tests.py
erp/base/storage/urls.py
erp/base/storage/views.py
erp/derivative/__init__.py
erp/derivative/trading/__init__.py
erp/derivative/trading/admin.py
erp/derivative/trading/api.py
erp/derivative/trading/models.py
erp/derivative/trading/serializers.py
erp/derivative/trading/urls.py
erp/derivative/trading/views.py
erp/extras/__init__.py
erp/extras/admin.py
erp/extras/fields.py
erp/extras/models.py
erp/extras/views.py